extraneous_activity_delays/__init__.py
extraneous_activity_delays/config.py
extraneous_activity_delays/delay_discoverer.py
extraneous_activity_delays/enhance_with_delays.py
extraneous_activity_delays/prosimos/__init__.py
extraneous_activity_delays/prosimos/simulation_model_enhancer.py
extraneous_activity_delays/prosimos/simulator.py
extraneous_activity_delays/qbp/__init__.py
extraneous_activity_delays/qbp/simulation_model_enhancer.py
extraneous_activity_delays/qbp/simulator.py
extraneous_activity_delays/utils/__init__.py
extraneous_activity_delays/utils/bpmn_enhancement.py
extraneous_activity_delays/utils/file_manager.py
extraneous_activity_delays-2.2.1.dist-info/LICENSE
extraneous_activity_delays-2.2.1.dist-info/METADATA
extraneous_activity_delays-2.2.1.dist-info/WHEEL
extraneous_activity_delays-2.2.1.dist-info/RECORD
