Metadata-Version: 2.1
Name: extraneous-activity-delays
Version: 2.2.1
Summary: 
Author: David Chapela de la Campa
Author-email: david.chapela.delacampa@gmail.com
Requires-Python: >=3.9,<3.12
Classifier: Programming Language :: Python :: 3
Classifier: Programming Language :: Python :: 3.9
Classifier: Programming Language :: Python :: 3.10
Classifier: Programming Language :: Python :: 3.11
Requires-Dist: hyperopt (>=0.2.7,<0.3.0)
Requires-Dist: log-distance-measures (>=2.0.0,<3.0.0)
Requires-Dist: lxml (>=5.3.0,<6.0.0)
Requires-Dist: pix-framework (>=0.13.17,<0.14.0)
Requires-Dist: prosimos (>=2.0.6,<3.0.0)
